choix/__init__.py
choix/convergence.py
choix/ep.py
choix/lsr.py
choix/mm.py
choix/opt.py
choix/py.typed
choix/typing.py
choix/utils.py
choix-0.4.1.dist-info/licenses/LICENSE
choix-0.4.1.dist-info/WHEEL
choix-0.4.1.dist-info/METADATA
choix-0.4.1.dist-info/RECORD
