Metadata-Version: 2.4
Name: choix
Version: 0.4.1
Summary: Inference algorithms for models based on Luce's choice axiom.
Keywords: statistics,ml,bradley-terry,plackett-luce,choice,comparison,ranking
Author: Lucas Maystre
Author-email: Lucas Maystre <lucas@maystre.ch>
License-Expression: MIT
License-File: LICENSE
Classifier: Development Status :: 4 - Beta
Classifier: License :: OSI Approved :: MIT License
Classifier: Intended Audience :: Science/Research
Classifier: Topic :: Scientific/Engineering :: Mathematics
Classifier: Topic :: Scientific/Engineering :: Artificial Intelligence
Classifier: Programming Language :: Python :: 3
Requires-Dist: numpy
Requires-Dist: scipy
Requires-Dist: networkx>=1,<3 ; extra == 'choicerank'
Requires-Dist: notebook ; extra == 'notebooks'
Requires-Dist: matplotlib ; extra == 'notebooks'
Requires-Python: >=3.10
Project-URL: Documentation, https://choix.lum.li/en/latest/
Project-URL: Homepage, https://github.com/lucasmaystre/choix
Project-URL: Issues, https://github.com/lucasmaystre/choix/issues
Project-URL: Repository, https://github.com/lucasmaystre/choix.git
Provides-Extra: choicerank
Provides-Extra: notebooks
